extended_int/__init__.py
extended_int/extended_int.py
extended_int/extended_integral.py
extended_int-0.7.dist-info/LICENSE
extended_int-0.7.dist-info/WHEEL
extended_int-0.7.dist-info/METADATA
extended_int-0.7.dist-info/RECORD
