Metadata-Version: 2.1
Name: extended-int
Version: 0.7
Summary: Python classes that provides support for extended integers (the set of integers, and infinity).
Home-page: https://github.com/NeilGirdhar/extended_int
License: MIT
Author: Neil Girdhar
Author-email: mistersheik@gmail.com
Requires-Python: >=3.9,<4
Classifier: Development Status :: 5 - Production/Stable
Classifier: Intended Audience :: Developers
Classifier: License :: OSI Approved :: MIT License
Classifier: Operating System :: OS Independent
Classifier: Programming Language :: Python
Classifier: Programming Language :: Python :: 3
Classifier: Programming Language :: Python :: 3.9
Classifier: Programming Language :: Python :: 3.10
Classifier: Programming Language :: Python :: 3
Classifier: Programming Language :: Python :: 3.9
Classifier: Typing :: Typed
Project-URL: Repository, https://github.com/NeilGirdhar/extended_int
